sequencelearn/__init__.py
sequencelearn/metrics.py
sequencelearn/point_tagger.py
sequencelearn/samples.py
sequencelearn/sequence_tagger.py
sequencelearn/util.py
sequencelearn/modules/__init__.py
sequencelearn/modules/crf_head.py
sequencelearn-0.0.9.dist-info/LICENSE
sequencelearn-0.0.9.dist-info/METADATA
sequencelearn-0.0.9.dist-info/WHEEL
sequencelearn-0.0.9.dist-info/top_level.txt
sequencelearn-0.0.9.dist-info/RECORD
