Metadata-Version: 2.1
Name: sequencelearn
Version: 0.0.9
Summary: Scikit-Learn like Named Entity Recognition modules
Home-page: https://github.com/code-kern-ai/sequencelearn
Author: Johannes Hötter
Author-email: johannes.hoetter@kern.ai
License: UNKNOWN
Keywords: kern.ai,machine learning,supervised learning,python
Platform: UNKNOWN
Classifier: Development Status :: 3 - Alpha
Classifier: Programming Language :: Python :: 3
Classifier: License :: OSI Approved :: MIT License
License-File: LICENSE
Requires-Dist: numpy (>=1.22.3)
Requires-Dist: scikit-learn (>=1.0.2)
Requires-Dist: scipy (>=1.8.0)
Requires-Dist: torch (>=1.11.0)
